HISTORY.txt
LICENSE
MANIFEST.in
README.md
requirements.txt
setup.cfg
setup.py
rcsb/__init__.py
rcsb.utils.repository.egg-info/PKG-INFO
rcsb.utils.repository.egg-info/SOURCES.txt
rcsb.utils.repository.egg-info/dependency_links.txt
rcsb.utils.repository.egg-info/not-zip-safe
rcsb.utils.repository.egg-info/requires.txt
rcsb.utils.repository.egg-info/top_level.txt
rcsb/utils/__init__.py
rcsb/utils/repository/CurrentHoldingsProvider.py
rcsb/utils/repository/RemovedHoldingsProvider.py
rcsb/utils/repository/RepositoryProvider.py
rcsb/utils/repository/ScanRepoUtil.py
rcsb/utils/repository/UnreleasedHoldingsProvider.py
rcsb/utils/repository/UpdateHoldingsProvider.py
rcsb/utils/repository/__init__.py